cira_classic/__init__.py
cira_classic/logging.py
cira_classic-1.0.4.dist-info/LICENSE.txt
cira_classic-1.0.4.dist-info/METADATA
cira_classic-1.0.4.dist-info/WHEEL
cira_classic-1.0.4.dist-info/top_level.txt
cira_classic-1.0.4.dist-info/RECORD
