Metadata-Version: 2.1
Name: cira-classic
Version: 1.0.4
Summary: A older style of the cira library.
Home-page: https://github.com/AxelGard/cira-classic/
Author: Axel Gard
Author-email: axel.gard@tutanota.com
License: MIT
Platform: UNKNOWN
Classifier: Development Status :: 4 - Beta
Classifier: Topic :: Office/Business :: Financial
Classifier: Programming Language :: Python :: 3.6
Classifier: License :: OSI Approved :: MIT License
Classifier: Programming Language :: Python :: 3.6
Classifier: Programming Language :: Python :: 3.7
Classifier: Programming Language :: Python :: 3.8
Requires-Dist: alpaca-trade-api
